safe_env/__init__.py
safe_env/__main__.py
safe_env/api.py
safe_env/appcontext.py
safe_env/cli.py
safe_env/envmanager.py
safe_env/utils.py
safe_env/version.py
safe_env/cache_providers/__init__.py
safe_env/cache_providers/azure_keyvault_cache.py
safe_env/cache_providers/base_cache_provider.py
safe_env/cache_providers/keyring_cache.py
safe_env/cache_providers/memory_cache.py
safe_env/models/__init__.py
safe_env/models/config.py
safe_env/models/resolver_results.py
safe_env/models/resolvers.py
safe_env/models/ui.py
safe_env/resolvers/__init__.py
safe_env/resolvers/auth.py
safe_env/resolvers/auth_keeper.py
safe_env/resolvers/cache.py
safe_env/resolvers/callables.py
safe_env/resolvers/callables_azure.py
safe_env/resolvers/callables_azuredevops.py
safe_env/resolvers/callables_keeper.py
safe_env/resolvers/callables_keyring.py
safe_env/resolvers/delayedcallable.py
safe_env/resolvers/resolvermanager.py
safe_env-0.1.5.dist-info/METADATA
safe_env-0.1.5.dist-info/WHEEL
safe_env-0.1.5.dist-info/entry_points.txt
safe_env-0.1.5.dist-info/licenses/LICENSE
safe_env-0.1.5.dist-info/RECORD
