Metadata-Version: 2.4
Name: safe-env
Version: 0.1.5
Summary: Safe Environment Manager allows to manage secrets in environment variables in a safe way.
Project-URL: Documentation, https://antonsmislevics.github.io/safe-env
Project-URL: Repository, https://github.com/antonsmislevics/safe-env.git
Author: Antons Mislevics
License-File: LICENSE
Requires-Python: >=3.10
Requires-Dist: artifacts-keyring>=0.4.0
Requires-Dist: azure-identity>=1.19.0
Requires-Dist: azure-keyvault-certificates>=4.9.0
Requires-Dist: azure-keyvault-secrets>=4.9.0
Requires-Dist: fsspec>=2024.12.0
Requires-Dist: jmespath>=1.0.1
Requires-Dist: keepercommander>=17.1.8
Requires-Dist: keyring>=25.5.0
Requires-Dist: omegaconf>=2.3.0
Requires-Dist: pydantic>=2.10.2
Requires-Dist: pyyaml>=6.0.2
Requires-Dist: tabulate>=0.9.0
Requires-Dist: tqdm>=4.67.1
Requires-Dist: typer>=0.14.0
